{
    "country": "INDIA",
    "format": "T20",
    "international": null,
    "match": {
        "battingTeam": {
            "batsman": {
                "id": "13266234768809",
                "isRightHanded": true,
                "name": "HASARANGA"
            },
            "batsmanPartner": {
                "id": "12921704446796",
                "isRightHanded": false,
                "name": "JOSH HAZLEWOOD"
            },
            "home": true,
            "id": "12865944325687",
            "name": "BANGALORE-ROYAL-CHALLENGERS"
        },
        "bowlingTeam": {
            "bowler": {
                "id": "13137486591693",
                "isRightHanded": false,
                "name": "T NATARAJAN",
                "spell": 2
            },
            "bowlerPartner": {
                "id": null,
                "isRightHanded": null,
                "name": null
            },
            "home": false,
            "name": "SUNRISERS-HYDERABAD"
        },
        "delivery": {
            "additionalEventInformation": {
                "dropped": null
            },
            "deliveryNumber": {
                "ball": 1,
                "day": 1,
                "innings": 1,
                "over": 16
            },
            "deliveryType": "Seam",
            "fielderPosition": {
                "1st Slip": false,
                "2nd Slip": false,
                "3rd Slip": false,
                "4th Slip": false,
                "5th Slip": false,
                "Backwards Point": false,
                "Cover": false,
                "Cow Corner": false,
                "Deep Backwards Square Leg": false,
                "Deep Cover": false,
                "Deep Extra Cover": false,
                "Deep Mid Wicket": false,
                "Deep Point": false,
                "Deep Square Leg": false,
                "Extra Cover": false,
                "Fine Leg": false,
                "Fly Slip": false,
                "Gully": false,
                "Leg Gully": false,
                "Leg Slip": false,
                "Long Leg": false,
                "Long-off": false,
                "Long-on": false,
                "Mid Wicket": false,
                "Mid-off": false,
                "Mid-on": false,
                "Point": false,
                "Short Extra Cover": false,
                "Short Fine Leg": false,
                "Short Leg": false,
                "Short Mid-wicket": false,
                "Silly Mid-off": false,
                "Silly Point": false,
                "Square Leg": false,
                "Third Man": false,
                "Wicket Keeper": false
            },
            "isPavilionEnd": true,
            "round": false,
            "scoringInformation": {
                "boundary": null,
                "extrasScore": 0,
                "extrasType": "None",
                "overthrowScore": null,
                "score": 0,
                "wicket": {
                    "isWicket": false,
                    "wicketType": null,
                    "wicketsTaken": null
                }
            },
            "shotInformation": {
                "batsmanWeight": "Unset",
                "shotAttacked": "Defended",
                "shotPlayed": "Played",
                "shotTypeAdditional": "Defend"
            },
            "timecode": "704062370000000",
            "trajectory": {
                "batStatPosition": {
                    "x": 0,
                    "y": 0
                },
                "bounceAboveStumps": null,
                "bounceAngle": 7.088534406026457,
                "bouncePosition": {
                    "x": 7.485867,
                    "y": 0.192695,
                    "z": 0
                },
                "cof": 0.1092895258582626,
                "cor": 0.6102502413011989,
                "creasePosition": {
                    "x": -8.840473,
                    "y": -0.020356,
                    "z": 0.654438
                },
                "deviation": -0.222798803507378,
                "dropAngle": -11.12799595339352,
                "hitStumps": null,
                "impactPosition": {
                    "x": -8.727909,
                    "y": -0.016438,
                    "z": 0.647236
                },
                "initialAngle": -7.935211647461413,
                "landingPosition": {
                    "x": 0,
                    "y": 0,
                    "z": -999.900024
                },
                "length": null,
                "offBatAngle": 1000000,
                "offBatSpeed": -1,
                "pbr": 90.60858360935357,
                "reactionTime(to crease)": 0.519538879394531,
                "reactionTime(to interception)": 0.5031280517578125,
                "realDistance": 0,
                "releasePosition": {
                    "x": 8.340424549030402,
                    "y": 0.5131067161647912,
                    "z": 1.884046503473088
                },
                "releaseSpeed": 82.7841321800059,
                "spinRate": 0,
                "stumpPosition": {
                    "x": -10.06021916233384,
                    "y": -0.06302892735964133,
                    "z": 0.7239122360670891
                },
                "swing": 0.003091099115577777,
                "trajectoryData": "<Bounce Position>7.485867 0.192695 <Bounce Time> 5.58498355314339e-01<Acceleration>-2.59993892498922e-01  2.74632861596971e-01 -4.97143086182510e+00  <Pre Bounce Velocity>-3.37992060248599e+01 -9.90735391868562e-01 -6.64829293847291e+00  <Post Bounce Velocity>-3.26257526432189e+01 -1.08333040520258e+00  4.05712236994415e+00  <Post Bounce Acceleration>-2.41422900177571e-01  0.00000000000000e+00 -1.06000000000000e+01  <Bounce Height> 6.15369607339945e-02<Last Update Time> 0.00000000000000e+00<Kalman Filter Type>2<Predicted>false<Quality>1<Warning>false<Stop Y Acceleration Prediction Post Interception>true<xPositionAtBatsman>-8.72769631589554e+00<Track Approved>true<Interception Approved>true<DRS Approved>false<Zero Time> 7.04062370077366e+08<Trajectory Speed> 3.71792166282967e+01<Trajectory Speed Sent>true<Distance Of Six (m)>-1.00000000000000e+00<Speed Off Bat(mps)>-1.00000000000000e+00<Angle Off Bat (Degrees)> 1.00000000000000e+06<Momentum Multiplier>-1.00000000000000e+00<Software Version>\"D:\\Cricket\\Logger\\Logger_2021_02_18_Magneto.exe\"<Bat Hit (true/false)>false<Bat Impact Position> 0.00000000000000e+00  0.00000000000000e+00  <Batsman Weight>\"Unset\"<Swing Distance (m)> 9.57425337082596e-04<COF on home pitch> 1.00000000000000e+00<COR on home pitch> 1.00000000000000e+00<Reaction Time (To Popping Crease, s)> 5.19538879394531e-01<Bowler>\"bowler name\"<Bowling End>1<Delivery Time and Date>\"2022/04/23 20:52:52.004\"<Delivery Stumps Time and Date>\"2022/04/23 20:52:51.872\""
            }
        },
        "name": "BANGALORE-ROYAL-CHALLENGERS_SUNRISERS-HYDERABAD_T20_36_BRABOURNE-STADIUM-MUMBAI_13295196053249"
    },
    "tourName": "INDIA_22_MAR_13292774873183_STAR-IPL"
}