{
    "country": "INDIA",
    "format": "T20",
    "international": null,
    "match": {
        "battingTeam": {
            "batsman": {
                "id": "13183590754523",
                "isRightHanded": true,
                "name": "PRITHVI SHAW"
            },
            "batsmanPartner": {
                "id": "12900173444328",
                "isRightHanded": false,
                "name": "David Warner"
            },
            "home": false,
            "id": "13198259104850",
            "name": "DELHI-CAPITALS"
        },
        "bowlingTeam": {
            "bowler": {
                "id": "13281642472751",
                "isRightHanded": true,
                "name": "VENKATESH IYER",
                "spell": 0
            },
            "bowlerPartner": {
                "id": null,
                "isRightHanded": null,
                "name": null
            },
            "home": true,
            "name": "KOLKATA-KNIGHT-RIDERS"
        },
        "delivery": {
            "additionalEventInformation": {
                "dropped": null
            },
            "deliveryNumber": {
                "ball": 5,
                "day": 1,
                "innings": 1,
                "over": 8
            },
            "deliveryType": "Seam",
            "fielderPosition": {
                "1st Slip": false,
                "2nd Slip": false,
                "3rd Slip": false,
                "4th Slip": false,
                "5th Slip": false,
                "Backwards Point": false,
                "Cover": false,
                "Cow Corner": false,
                "Deep Backwards Square Leg": false,
                "Deep Cover": false,
                "Deep Extra Cover": false,
                "Deep Mid Wicket": false,
                "Deep Point": false,
                "Deep Square Leg": false,
                "Extra Cover": false,
                "Fine Leg": false,
                "Fly Slip": false,
                "Gully": false,
                "Leg Gully": false,
                "Leg Slip": false,
                "Long Leg": false,
                "Long-off": false,
                "Long-on": false,
                "Mid Wicket": false,
                "Mid-off": false,
                "Mid-on": false,
                "Point": false,
                "Short Extra Cover": false,
                "Short Fine Leg": false,
                "Short Leg": false,
                "Short Mid-wicket": false,
                "Silly Mid-off": false,
                "Silly Point": false,
                "Square Leg": false,
                "Third Man": false,
                "Wicket Keeper": false
            },
            "isPavilionEnd": true,
            "round": false,
            "scoringInformation": {
                "boundary": null,
                "extrasScore": 0,
                "extrasType": "None",
                "overthrowScore": null,
                "score": 4,
                "wicket": {
                    "isWicket": false,
                    "wicketType": null,
                    "wicketsTaken": null
                }
            },
            "shotInformation": {
                "batsmanWeight": "Unset",
                "shotAttacked": "Attacked",
                "shotPlayed": "Played",
                "shotTypeAdditional": "Cut"
            },
            "timecode": "702922260000000",
            "trajectory": {
                "batStatPosition": {
                    "x": 0,
                    "y": 0
                },
                "bounceAboveStumps": null,
                "bounceAngle": 9.821702541882631,
                "bouncePosition": {
                    "x": 9.060748,
                    "y": -0.73725,
                    "z": 0
                },
                "cof": 0.216905260052466,
                "cor": 0.6505781793104779,
                "creasePosition": {
                    "x": -8.84087,
                    "y": -0.765798,
                    "z": 1.049062
                },
                "deviation": -0.5029443509127295,
                "dropAngle": -13.65585077011942,
                "hitStumps": null,
                "impactPosition": {
                    "x": -9.033707,
                    "y": -0.766517,
                    "z": 1.064569
                },
                "initialAngle": -10.09654167184338,
                "landingPosition": {
                    "x": -100,
                    "y": -129,
                    "z": 5
                },
                "length": null,
                "offBatAngle": 1000000,
                "offBatSpeed": -1,
                "pbr": 85.8962008913251,
                "reactionTime(to crease)": 0.557624816894531,
                "reactionTime(to interception)": 0.5519485473632812,
                "realDistance": 0,
                "releasePosition": {
                    "x": 8.34114922705044,
                    "y": -0.7399671738710663,
                    "z": 1.998781998069694
                },
                "releaseSpeed": 79.51030279136248,
                "spinRate": 0,
                "stumpPosition": {
                    "x": -10.06020535926583,
                    "y": -0.7703523431210936,
                    "z": 1.13924247911704
                },
                "swing": 0.5454902857478301,
                "trajectoryData": "<Bounce Position>9.060748 -0.737250 <Bounce Time> 4.79666014107922e-01<Acceleration>-2.51129803770163e-01  1.16150974489906e+00 -6.15601700805813e+00  <Pre Bounce Velocity>-3.26468744901212e+01  1.70292930753203e-01 -7.93180419565620e+00  <Post Bounce Velocity>-2.98073922316099e+01 -1.06170590799411e-01  5.16025873225722e+00  <Post Bounce Acceleration>-1.63234372450606e-01  0.00000000000000e+00 -1.05317672041833e+01  <Bounce Height> 4.22481199796585e-02<Last Update Time> 0.00000000000000e+00<Kalman Filter Type>2<Predicted>false<Quality>1<Warning>false<Stop Y Acceleration Prediction Post Interception>true<xPositionAtBatsman>-9.03364188288279e+00<Track Approved>true<Interception Approved>true<DRS Approved>false<Zero Time> 7.02922260461368e+08<Trajectory Speed> 3.56776445176908e+01<Trajectory Speed Sent>true<Distance Of Six (m)>-1.00000000000000e+00<Speed Off Bat(mps)>-1.00000000000000e+00<Angle Off Bat (Degrees)> 1.00000000000000e+06<Momentum Multiplier>-1.00000000000000e+00<Software Version>\"D:\\Cricket\\Logger\\Logger_2021_02_18_Magneto.exe\"<Bat Hit (true/false)>false<Bat Impact Position> 0.00000000000000e+00  0.00000000000000e+00  <Batsman Weight>\"Unset\"<Swing Distance (m)> 4.29003820545639e-02<COF on home pitch> 1.00000000000000e+00<COR on home pitch> 1.00000000000000e+00<Reaction Time (To Popping Crease, s)> 5.57624816894531e-01<Bowler>\"bowler name\"<Bowling End>1<Delivery Time and Date>\"2022/04/10 16:11:01.580\"<Delivery Stumps Time and Date>\"2022/04/10 16:11:01.327\""
            }
        },
        "name": "KOLKATA-KNIGHT-RIDERS_DELHI-CAPITALS_T20_19_BRABOURNE-STADIUM-MUMBAI_13294008820157"
    },
    "tourName": "INDIA_22_MAR_13292774873183_STAR-IPL"
}