{
    "country": "INDIA",
    "format": "T20",
    "international": null,
    "match": {
        "battingTeam": {
            "batsman": {
                "id": "12899813945843",
                "isRightHanded": true,
                "name": "Jos Buttler"
            },
            "batsmanPartner": {
                "id": "12977475908091",
                "isRightHanded": true,
                "name": "Sanju Samson"
            },
            "home": true,
            "id": "12865946356000",
            "name": "RAJASTHAN-ROYALS"
        },
        "bowlingTeam": {
            "bowler": {
                "id": "12866689523297",
                "isRightHanded": true,
                "name": "Andre Russell",
                "spell": 0
            },
            "bowlerPartner": {
                "id": null,
                "isRightHanded": null,
                "name": null
            },
            "home": false,
            "name": "KOLKATA-KNIGHT-RIDERS"
        },
        "delivery": {
            "additionalEventInformation": {
                "dropped": null
            },
            "deliveryNumber": {
                "ball": 1,
                "day": 1,
                "innings": 1,
                "over": 16
            },
            "deliveryType": "Seam",
            "fielderPosition": {
                "1st Slip": false,
                "2nd Slip": false,
                "3rd Slip": false,
                "4th Slip": false,
                "5th Slip": false,
                "Backwards Point": false,
                "Cover": false,
                "Cow Corner": false,
                "Deep Backwards Square Leg": false,
                "Deep Cover": false,
                "Deep Extra Cover": false,
                "Deep Mid Wicket": false,
                "Deep Point": false,
                "Deep Square Leg": false,
                "Extra Cover": false,
                "Fine Leg": false,
                "Fly Slip": false,
                "Gully": false,
                "Leg Gully": false,
                "Leg Slip": false,
                "Long Leg": false,
                "Long-off": false,
                "Long-on": false,
                "Mid Wicket": false,
                "Mid-off": false,
                "Mid-on": false,
                "Point": false,
                "Short Extra Cover": false,
                "Short Fine Leg": false,
                "Short Leg": false,
                "Short Mid-wicket": false,
                "Silly Mid-off": false,
                "Silly Point": false,
                "Square Leg": false,
                "Third Man": false,
                "Wicket Keeper": false
            },
            "isPavilionEnd": false,
            "round": false,
            "scoringInformation": {
                "boundary": null,
                "extrasScore": 0,
                "extrasType": "None",
                "overthrowScore": null,
                "score": 1,
                "wicket": {
                    "isWicket": false,
                    "wicketType": null,
                    "wicketsTaken": null
                }
            },
            "shotInformation": {
                "batsmanWeight": "Unset",
                "shotAttacked": "Attacked",
                "shotPlayed": "Played",
                "shotTypeAdditional": "Glance"
            },
            "timecode": "703630282000000",
            "trajectory": {
                "batStatPosition": {
                    "x": 0,
                    "y": 0
                },
                "bounceAboveStumps": null,
                "bounceAngle": 10.18320215021376,
                "bouncePosition": {
                    "x": 7.943636,
                    "y": -0.136445,
                    "z": 0
                },
                "cof": 0.2644811990122857,
                "cor": 0.6617607717265502,
                "creasePosition": {
                    "x": -8.840907,
                    "y": 0.157648,
                    "z": 0.910763
                },
                "deviation": 1.399246758308367,
                "dropAngle": -13.62286281925703,
                "hitStumps": null,
                "impactPosition": {
                    "x": -8.521887,
                    "y": 0.143438,
                    "z": 0.885197
                },
                "initialAngle": -8.141533322099432,
                "landingPosition": {
                    "x": -40,
                    "y": 132,
                    "z": 0
                },
                "length": null,
                "offBatAngle": 1000000,
                "offBatSpeed": -1,
                "pbr": 82.81599585775396,
                "reactionTime(to crease)": 0.617305755615234,
                "reactionTime(to interception)": 0.5892562866210938,
                "realDistance": 0,
                "releasePosition": {
                    "x": 8.340497677244603,
                    "y": -0.4065642100944539,
                    "z": 2.035283324694706
                },
                "releaseSpeed": 71.96601527685661,
                "spinRate": 0,
                "stumpPosition": {
                    "x": -10.06017114222956,
                    "y": 0.2122025436106658,
                    "z": 0.9933121720091038
                },
                "swing": -0.8113419974022072,
                "trajectoryData": "<Bounce Position>7.943636 -0.136445 <Bounce Time> 5.11475682269588e-01<Acceleration>-2.26671268685964e-01 -1.44997195465057e+00 -7.57845380257032e+00  <Pre Bounce Velocity>-2.94672649291753e+01  5.43963414040633e-01 -7.14132941253551e+00  <Post Bounce Velocity>-2.63094337378947e+01  1.12882171722244e+00  4.72585166319301e+00  <Post Bounce Acceleration>-1.47336324645877e-01  0.00000000000000e+00 -1.06000000000000e+01  <Bounce Height> 3.92769021897121e-02<Last Update Time> 0.00000000000000e+00<Kalman Filter Type>2<Predicted>false<Quality>1<Warning>false<Stop Y Acceleration Prediction Post Interception>true<xPositionAtBatsman>-8.52180451240907e+00<Track Approved>true<Interception Approved>true<DRS Approved>false<Zero Time> 7.03630282121740e+08<Trajectory Speed> 3.21707712458009e+01<Trajectory Speed Sent>true<Distance Of Six (m)>-1.00000000000000e+00<Speed Off Bat(mps)>-1.00000000000000e+00<Angle Off Bat (Degrees)> 1.00000000000000e+06<Momentum Multiplier>-1.00000000000000e+00<Software Version>\"D:\\Cricket\\Logger\\Logger_2021_02_18_Magneto.exe\"<Bat Hit (true/false)>false<Bat Impact Position> 0.00000000000000e+00  0.00000000000000e+00  <Batsman Weight>\"Unset\"<Swing Distance (m)>-7.10424317656829e-02<COF on home pitch> 1.00000000000000e+00<COR on home pitch> 1.00000000000000e+00<Reaction Time (To Popping Crease, s)> 6.17305755615234e-01<Bowler>\"bowler name\"<Bowling End>0<Delivery Time and Date>\"2022/04/18 20:51:22.317\"<Delivery Stumps Time and Date>\"2022/04/18 20:51:22.345\""
            }
        },
        "name": "RAJASTHAN-ROYALS_KOLKATA-KNIGHT-RIDERS_T20_30_BRABOURNE-STADIUM-MUMBAI_13294759823194"
    },
    "tourName": "INDIA_22_MAR_13292774873183_STAR-IPL"
}