{
    "country": "INDIA",
    "format": "T20",
    "international": null,
    "match": {
        "battingTeam": {
            "batsman": {
                "id": "12900173444328",
                "isRightHanded": false,
                "name": "David Warner"
            },
            "batsmanPartner": {
                "id": "13183590754523",
                "isRightHanded": true,
                "name": "PRITHVI SHAW"
            },
            "home": false,
            "id": "13198259104850",
            "name": "DELHI-CAPITALS"
        },
        "bowlingTeam": {
            "bowler": {
                "id": "12946643670784",
                "isRightHanded": true,
                "name": "Umesh Yadav",
                "spell": 0
            },
            "bowlerPartner": {
                "id": null,
                "isRightHanded": null,
                "name": null
            },
            "home": true,
            "name": "KOLKATA-KNIGHT-RIDERS"
        },
        "delivery": {
            "additionalEventInformation": {
                "dropped": null
            },
            "deliveryNumber": {
                "ball": 3,
                "day": 1,
                "innings": 1,
                "over": 3
            },
            "deliveryType": "Seam",
            "fielderPosition": {
                "1st Slip": false,
                "2nd Slip": false,
                "3rd Slip": false,
                "4th Slip": false,
                "5th Slip": false,
                "Backwards Point": false,
                "Cover": false,
                "Cow Corner": false,
                "Deep Backwards Square Leg": false,
                "Deep Cover": false,
                "Deep Extra Cover": false,
                "Deep Mid Wicket": false,
                "Deep Point": false,
                "Deep Square Leg": false,
                "Extra Cover": false,
                "Fine Leg": false,
                "Fly Slip": false,
                "Gully": false,
                "Leg Gully": false,
                "Leg Slip": false,
                "Long Leg": false,
                "Long-off": false,
                "Long-on": false,
                "Mid Wicket": false,
                "Mid-off": false,
                "Mid-on": false,
                "Point": false,
                "Short Extra Cover": false,
                "Short Fine Leg": false,
                "Short Leg": false,
                "Short Mid-wicket": false,
                "Silly Mid-off": false,
                "Silly Point": false,
                "Square Leg": false,
                "Third Man": false,
                "Wicket Keeper": false
            },
            "isPavilionEnd": false,
            "round": false,
            "scoringInformation": {
                "boundary": null,
                "extrasScore": 0,
                "extrasType": "None",
                "overthrowScore": null,
                "score": 1,
                "wicket": {
                    "isWicket": false,
                    "wicketType": null,
                    "wicketsTaken": null
                }
            },
            "shotInformation": {
                "batsmanWeight": "Unset",
                "shotAttacked": "Attacked",
                "shotPlayed": "Played",
                "shotTypeAdditional": "Pull-Hook"
            },
            "timecode": "702920479000000",
            "trajectory": {
                "batStatPosition": {
                    "x": 0,
                    "y": 0
                },
                "bounceAboveStumps": null,
                "bounceAngle": 7.972873521434218,
                "bouncePosition": {
                    "x": 6.641565,
                    "y": -0.161089,
                    "z": 0
                },
                "cof": 0.1339287959620101,
                "cor": 0.6721335064921715,
                "creasePosition": {
                    "x": -8.84097,
                    "y": -0.042337,
                    "z": 0.670379
                },
                "deviation": -0.3997018719643722,
                "dropAngle": -11.26168956228957,
                "hitStumps": null,
                "impactPosition": {
                    "x": -8.321773,
                    "y": -0.053922,
                    "z": 0.619962
                },
                "initialAngle": -7.607200044725595,
                "landingPosition": {
                    "x": 22,
                    "y": -38,
                    "z": 0
                },
                "length": null,
                "offBatAngle": 1000000,
                "offBatSpeed": -1,
                "pbr": 97.42714637762472,
                "reactionTime(to crease)": 0.483558654785156,
                "reactionTime(to interception)": 0.4556808471679688,
                "realDistance": 0,
                "releasePosition": {
                    "x": 8.34120158504114,
                    "y": -0.4419772996059107,
                    "z": 1.971604593063278
                },
                "releaseSpeed": 88.98268228635578,
                "spinRate": 0,
                "stumpPosition": {
                    "x": -10.06010250512016,
                    "y": -0.01494805583235873,
                    "z": 0.7792836334514783
                },
                "swing": 0.5008381106500013,
                "trajectoryData": "<Bounce Position>6.641565 -0.161089 <Bounce Time> 6.08259340156856e-01<Acceleration>-2.78288689269371e-01  8.09801770636794e-01 -6.21828037947319e+00  <Pre Bounce Velocity>-3.61775296050183e+01  1.02864703854654e+00 -7.20383139676981e+00  <Post Bounce Velocity>-3.45709211190981e+01  7.41644136882534e-01  4.84193645688929e+00  <Post Bounce Acceleration>-2.58410925750130e-01  0.00000000000000e+00 -1.06000000000000e+01  <Bounce Height> 3.09723003961873e-02<Last Update Time> 0.00000000000000e+00<Kalman Filter Type>2<Predicted>false<Quality>1<Warning>false<Stop Y Acceleration Prediction Post Interception>true<xPositionAtBatsman>-8.32177110067706e+00<Track Approved>true<Interception Approved>true<DRS Approved>false<Zero Time> 7.02920479506114e+08<Trajectory Speed> 3.97776854208117e+01<Trajectory Speed Sent>true<Distance Of Six (m)>-1.00000000000000e+00<Speed Off Bat(mps)>-1.00000000000000e+00<Angle Off Bat (Degrees)> 1.00000000000000e+06<Momentum Multiplier>-1.00000000000000e+00<Software Version>\"D:\\Cricket\\Logger\\Logger_2021_02_18_Magneto.exe\"<Bat Hit (true/false)>false<Bat Impact Position> 0.00000000000000e+00  0.00000000000000e+00  <Batsman Weight>\"Unset\"<Swing Distance (m)> 4.93422322430397e-02<COF on home pitch> 1.00000000000000e+00<COR on home pitch> 1.00000000000000e+00<Reaction Time (To Popping Crease, s)> 4.83558654785156e-01<Bowler>\"bowler name\"<Bowling End>0<Delivery Time and Date>\"2022/04/10 15:41:20.609\"<Delivery Stumps Time and Date>\"2022/04/10 15:41:20.374\""
            }
        },
        "name": "KOLKATA-KNIGHT-RIDERS_DELHI-CAPITALS_T20_19_BRABOURNE-STADIUM-MUMBAI_13294008820157"
    },
    "tourName": "INDIA_22_MAR_13292774873183_STAR-IPL"
}