{
    "country": "INDIA",
    "format": "T20",
    "international": null,
    "match": {
        "battingTeam": {
            "batsman": {
                "id": "12865945221765",
                "isRightHanded": true,
                "name": "Wriddhiman Saha"
            },
            "batsmanPartner": {
                "id": "12918673942000",
                "isRightHanded": false,
                "name": "David Miller"
            },
            "home": true,
            "id": "13292948245806",
            "name": "GUJARAT-TITANS"
        },
        "bowlingTeam": {
            "bowler": {
                "id": "13218899665491",
                "isRightHanded": false,
                "name": "MARCO JANSEN",
                "spell": 2
            },
            "bowlerPartner": {
                "id": null,
                "isRightHanded": null,
                "name": null
            },
            "home": false,
            "name": "SUNRISERS-HYDERABAD"
        },
        "delivery": {
            "additionalEventInformation": {
                "dropped": null
            },
            "deliveryNumber": {
                "ball": 3,
                "day": 1,
                "innings": 2,
                "over": 12
            },
            "deliveryType": "Seam",
            "fielderPosition": {
                "1st Slip": false,
                "2nd Slip": false,
                "3rd Slip": false,
                "4th Slip": false,
                "5th Slip": false,
                "Backwards Point": false,
                "Cover": false,
                "Cow Corner": false,
                "Deep Backwards Square Leg": false,
                "Deep Cover": false,
                "Deep Extra Cover": false,
                "Deep Mid Wicket": false,
                "Deep Point": false,
                "Deep Square Leg": false,
                "Extra Cover": false,
                "Fine Leg": false,
                "Fly Slip": false,
                "Gully": false,
                "Leg Gully": false,
                "Leg Slip": false,
                "Long Leg": false,
                "Long-off": false,
                "Long-on": false,
                "Mid Wicket": false,
                "Mid-off": false,
                "Mid-on": false,
                "Point": false,
                "Short Extra Cover": false,
                "Short Fine Leg": false,
                "Short Leg": false,
                "Short Mid-wicket": false,
                "Silly Mid-off": false,
                "Silly Point": false,
                "Square Leg": false,
                "Third Man": false,
                "Wicket Keeper": false
            },
            "isPavilionEnd": false,
            "round": false,
            "scoringInformation": {
                "boundary": null,
                "extrasScore": 1,
                "extrasType": "Wide",
                "overthrowScore": null,
                "score": 0,
                "wicket": {
                    "isWicket": false,
                    "wicketType": null,
                    "wicketsTaken": null
                }
            },
            "shotInformation": {
                "batsmanWeight": "Unset",
                "shotAttacked": "Attacked",
                "shotPlayed": "Played",
                "shotTypeAdditional": "None"
            },
            "timecode": "704413833000000",
            "trajectory": {
                "batStatPosition": {
                    "x": 0,
                    "y": 0
                },
                "bounceAboveStumps": null,
                "bounceAngle": 9.261464226252825,
                "bouncePosition": {
                    "x": 2.591338,
                    "y": -0.815341,
                    "z": 0
                },
                "cof": 0.2930159126070156,
                "cor": 0.6885181712311336,
                "creasePosition": {
                    "x": -8.840943,
                    "y": -0.954055,
                    "z": 0.266608
                },
                "deviation": -1.502474998762534,
                "dropAngle": -11.94871970885388,
                "hitStumps": null,
                "impactPosition": {
                    "x": -999.9,
                    "y": -999.9,
                    "z": -999.9
                },
                "initialAngle": -4.34479109259092,
                "landingPosition": {
                    "x": 0,
                    "y": 0,
                    "z": -999.900024
                },
                "length": null,
                "offBatAngle": 1000000,
                "offBatSpeed": -1,
                "pbr": 83.97613442396849,
                "reactionTime(to crease)": 0.552726745605469,
                "reactionTime(to interception)": 0.5835914611816406,
                "realDistance": 0,
                "releasePosition": {
                    "x": 8.34071082970334,
                    "y": 0.4307612449093882,
                    "z": 2.269451036891998
                },
                "releaseSpeed": 77.21598649652152,
                "spinRate": 0,
                "stumpPosition": {
                    "x": -10.06004684782734,
                    "y": -1.078582611622916,
                    "z": 0.4334507076463742
                },
                "swing": 0.4988351269938192,
                "trajectoryData": "<Bounce Position>2.591338 -0.815341 <Bounce Time> 6.97697554269392e-01<Acceleration>-2.35254681423259e-01  1.18091876723859e+00 -7.92451504394270e+00  <Pre Bounce Velocity>-3.05831085850236e+01 -2.26630046260837e+00 -6.47203697093783e+00  <Post Bounce Velocity>-2.73271071492334e+01 -2.74712716822524e+00  4.45611505937040e+00  <Post Bounce Acceleration>-2.18450775607312e-01  0.00000000000000e+00 -1.06000000000000e+01  <Bounce Height> 5.51126803368332e-02<Last Update Time> 0.00000000000000e+00<Kalman Filter Type>2<Predicted>false<Quality>1<Warning>false<Stop Y Acceleration Prediction Post Interception>true<xPositionAtBatsman>-1.00584001541138e+01<Track Approved>true<Interception Approved>false<DRS Approved>false<Zero Time> 7.04413833768982e+08<Trajectory Speed> 3.45176515406891e+01<Trajectory Speed Sent>true<Distance Of Six (m)>-1.00000000000000e+00<Speed Off Bat(mps)>-1.00000000000000e+00<Angle Off Bat (Degrees)> 1.00000000000000e+06<Momentum Multiplier>-1.00000000000000e+00<Software Version>\"D:\\Cricket\\Logger\\Logger_2021_02_18_Magneto.exe\"<Bat Hit (true/false)>false<Bat Impact Position> 0.00000000000000e+00  0.00000000000000e+00  <Batsman Weight>\"Unset\"<Swing Distance (m)> 6.38856789270303e-02<COF on home pitch> 1.00000000000000e+00<COR on home pitch> 1.00000000000000e+00<Reaction Time (To Popping Crease, s)> 5.52726745605469e-01<Bowler>\"bowler name\"<Bowling End>0<Delivery Time and Date>\"2022/04/27 22:30:34.257\"<Delivery Stumps Time and Date>\"2022/04/27 22:30:34.186\""
            }
        },
        "name": "GUJARAT-TITANS_SUNRISERS-HYDERABAD_T20_40_WANKHEDE-STADIUM-MUMBAI_13295540887956"
    },
    "tourName": "INDIA_22_MAR_13292774873183_STAR-IPL"
}